LICENSE
MANIFEST.in
README
setup.py
MarkdownPP/MarkdownPP.py
MarkdownPP/Module.py
MarkdownPP/Processor.py
MarkdownPP/Transform.py
MarkdownPP/__init__.py
MarkdownPP/main.py
MarkdownPP.egg-info/PKG-INFO
MarkdownPP.egg-info/SOURCES.txt
MarkdownPP.egg-info/dependency_links.txt
MarkdownPP.egg-info/entry_points.txt
MarkdownPP.egg-info/requires.txt
MarkdownPP.egg-info/top_level.txt
MarkdownPP/Modules/Include.py
MarkdownPP/Modules/IncludeCode.py
MarkdownPP/Modules/IncludeURL.py
MarkdownPP/Modules/LaTeXRender.py
MarkdownPP/Modules/Reference.py
MarkdownPP/Modules/TableOfContents.py
MarkdownPP/Modules/YoutubeEmbed.py
MarkdownPP/Modules/__init__.py
test/test.py